simply_mcp/__init__.py
simply_mcp/py.typed
simply_mcp/api/__init__.py
simply_mcp/api/builder.py
simply_mcp/api/decorators.py
simply_mcp/api/functional.py
simply_mcp/api/programmatic.py
simply_mcp/cli/__init__.py
simply_mcp/cli/build.py
simply_mcp/cli/bundle.py
simply_mcp/cli/config.py
simply_mcp/cli/dev.py
simply_mcp/cli/list_cmd.py
simply_mcp/cli/main.py
simply_mcp/cli/run.py
simply_mcp/cli/utils.py
simply_mcp/cli/watch.py
simply_mcp/core/__init__.py
simply_mcp/core/auth.py
simply_mcp/core/config.py
simply_mcp/core/errors.py
simply_mcp/core/http_config.py
simply_mcp/core/logger.py
simply_mcp/core/rate_limit.py
simply_mcp/core/registry.py
simply_mcp/core/security.py
simply_mcp/core/server.py
simply_mcp/core/types.py
simply_mcp/core/ui_resource.py
simply_mcp/core/ui_types.py
simply_mcp/features/__init__.py
simply_mcp/features/binary.py
simply_mcp/features/progress.py
simply_mcp/handlers/__init__.py
simply_mcp/monitoring/__init__.py
simply_mcp/monitoring/http_metrics.py
simply_mcp/security/__init__.py
simply_mcp/security/auth.py
simply_mcp/security/rate_limiter.py
simply_mcp/transports/__init__.py
simply_mcp/transports/factory.py
simply_mcp/transports/http.py
simply_mcp/transports/http_transport.py
simply_mcp/transports/middleware.py
simply_mcp/transports/sse.py
simply_mcp/transports/stdio.py
simply_mcp/validation/__init__.py
simply_mcp/validation/schema.py
simply_mcp-0.1.0.dist-info/METADATA
simply_mcp-0.1.0.dist-info/WHEEL
simply_mcp-0.1.0.dist-info/entry_points.txt
simply_mcp-0.1.0.dist-info/RECORD
