Metadata-Version: 2.4
Name: simply-mcp
Version: 0.1.0
Summary: A modern Python framework for building MCP servers with multiple API styles
Project-URL: Homepage, https://github.com/Clockwork-Innovations/simply-mcp-py
Project-URL: Documentation, https://simply-mcp-py.readthedocs.io
Project-URL: Repository, https://github.com/Clockwork-Innovations/simply-mcp-py
Project-URL: Issues, https://github.com/Clockwork-Innovations/simply-mcp-py/issues
Project-URL: Changelog, https://github.com/Clockwork-Innovations/simply-mcp-py/blob/main/CHANGELOG.md
Author-email: Clockwork Innovations <info@clockwork-innovations.com>
License: MIT
Keywords: ai,anthropic,framework,llm,mcp,model-context-protocol,server
Classifier: Development Status :: 3 - Alpha
Classifier: Intended Audience :: Developers
Classifier: License :: OSI Approved :: MIT License
Classifier: Programming Language :: Python :: 3
Classifier: Programming Language :: Python :: 3.10
Classifier: Programming Language :: Python :: 3.11
Classifier: Programming Language :: Python :: 3.12
Classifier: Topic :: Scientific/Engineering :: Artificial Intelligence
Classifier: Topic :: Software Development :: Libraries :: Python Modules
Requires-Python: >=3.10
Requires-Dist: aiohttp-cors>=0.7.0
Requires-Dist: aiohttp>=3.9.0
Requires-Dist: click>=8.0.0
Requires-Dist: cryptography>=41.0.0
Requires-Dist: mcp>=0.1.0
Requires-Dist: pydantic-settings>=2.0.0
Requires-Dist: pydantic>=2.0.0
Requires-Dist: pyjwt>=2.8.0
Requires-Dist: python-dotenv>=1.0.0
Requires-Dist: python-json-logger>=2.0.0
Requires-Dist: rich>=13.0.0
Requires-Dist: tomli>=2.0.0; python_version < '3.11'
Requires-Dist: typing-extensions>=4.0.0
Requires-Dist: watchdog>=4.0.0
Provides-Extra: bundling
Requires-Dist: pyinstaller>=5.0.0; extra == 'bundling'
Provides-Extra: dev
Requires-Dist: aiosqlite>=0.19.0; extra == 'dev'
Requires-Dist: black>=23.0.0; extra == 'dev'
Requires-Dist: build>=1.0.0; extra == 'dev'
Requires-Dist: httpx>=0.24.0; extra == 'dev'
Requires-Dist: mypy>=1.0.0; extra == 'dev'
Requires-Dist: pre-commit>=3.0.0; extra == 'dev'
Requires-Dist: pytest-asyncio>=0.21.0; extra == 'dev'
Requires-Dist: pytest-cov>=4.0.0; extra == 'dev'
Requires-Dist: pytest-mock>=3.10.0; extra == 'dev'
Requires-Dist: pytest>=7.0.0; extra == 'dev'
Requires-Dist: ruff>=0.1.0; extra == 'dev'
Requires-Dist: tomli>=2.0.0; extra == 'dev'
Requires-Dist: twine>=4.0.0; extra == 'dev'
Requires-Dist: types-pyinstaller>=6.0.0; extra == 'dev'
Provides-Extra: docs
Requires-Dist: mkdocs-gen-files>=0.5.0; extra == 'docs'
Requires-Dist: mkdocs-literate-nav>=0.6.0; extra == 'docs'
Requires-Dist: mkdocs-material>=9.4.0; extra == 'docs'
Requires-Dist: mkdocs-section-index>=0.3.0; extra == 'docs'
Requires-Dist: mkdocs>=1.5.0; extra == 'docs'
Requires-Dist: mkdocstrings[python]>=0.24.0; extra == 'docs'
